<?xml version="1.0" encoding="UTF-8"?>
<configuration>

    <!-- ========== 变量定义 ========== -->
    <springProperty scope="context" name="APP_NAME"  source="spring.application.name" defaultValue="finance-api"/>
    <springProperty scope="context" name="LOG_LEVEL" source="logging.level.com.finance.api" defaultValue="info"/>

    <!-- 日志存储目录 -->
    <property name="LOG_HOME" value="./logs"/>

    <!-- ========== 控制台输出 ========== -->
    <appender name="CONSOLE" class="ch.qos.logback.core.ConsoleAppender">
        <encoder class="ch.qos.logback.classic.encoder.PatternLayoutEncoder">
            <!-- 标准日志格式，兼容 logback 1.5.x -->
            <pattern>%d{yyyy-MM-dd HH:mm:ss.SSS} %5p ${PID:- } --- [%15.15t] %-40.40logger{39} : %m%n%ex</pattern>
            <charset>UTF-8</charset>
        </encoder>
    </appender>

    <!-- ========== 按天滚动文件输出（INFO 及以上） ========== -->
    <appender name="FILE_INFO" class="ch.qos.logback.core.rolling.RollingFileAppender">
        <file>${LOG_HOME}/${APP_NAME}.log</file>
        <rollingPolicy class="ch.qos.logback.core.rolling.TimeBasedRollingPolicy">
            <!-- 按天归档，保留 30 天 -->
            <fileNamePattern>${LOG_HOME}/${APP_NAME}.%d{yyyy-MM-dd}.log</fileNamePattern>
            <maxHistory>30</maxHistory>
            <totalSizeCap>1GB</totalSizeCap>
        </rollingPolicy>
        <encoder>
            <pattern>%d{yyyy-MM-dd HH:mm:ss.SSS} [%thread] %-5level %logger{50} - %msg%n</pattern>
            <charset>UTF-8</charset>
        </encoder>
        <filter class="ch.qos.logback.classic.filter.ThresholdFilter">
            <level>INFO</level>
        </filter>
    </appender>

    <!-- ========== 错误日志单独输出 ========== -->
    <appender name="FILE_ERROR" class="ch.qos.logback.core.rolling.RollingFileAppender">
        <file>${LOG_HOME}/${APP_NAME}-error.log</file>
        <rollingPolicy class="ch.qos.logback.core.rolling.TimeBasedRollingPolicy">
            <fileNamePattern>${LOG_HOME}/${APP_NAME}-error.%d{yyyy-MM-dd}.log</fileNamePattern>
            <maxHistory>30</maxHistory>
        </rollingPolicy>
        <encoder>
            <pattern>%d{yyyy-MM-dd HH:mm:ss.SSS} [%thread] %-5level %logger{50} - %msg%n</pattern>
            <charset>UTF-8</charset>
        </encoder>
        <filter class="ch.qos.logback.classic.filter.LevelFilter">
            <level>ERROR</level>
            <onMatch>ACCEPT</onMatch>
            <onMismatch>DENY</onMismatch>
        </filter>
    </appender>

    <!-- ========== 异步输出（提升性能） ========== -->
    <appender name="ASYNC_FILE" class="ch.qos.logback.classic.AsyncAppender">
        <queueSize>512</queueSize>
        <discardingThreshold>0</discardingThreshold>
        <neverBlock>true</neverBlock>
        <appender-ref ref="FILE_INFO"/>
    </appender>

    <!-- ========== 业务日志级别配置 ========== -->
    <!-- 项目自身包：根据 application.yml 中 logging.level.com.finance.api 控制 -->
    <logger name="com.finance.api" level="${LOG_LEVEL}" additivity="false">
        <appender-ref ref="CONSOLE"/>
        <appender-ref ref="ASYNC_FILE"/>
        <appender-ref ref="FILE_ERROR"/>
    </logger>

    <!-- MyBatisPlus SQL 日志（dev 环境输出，prod 环境不输出） -->
    <springProfile name="dev">
        <logger name="com.finance.api.mapper" level="DEBUG" additivity="false">
            <appender-ref ref="CONSOLE"/>
        </logger>
    </springProfile>

    <!-- 框架日志降噪 -->
    <logger name="org.springframework"      level="WARN"/>
    <logger name="org.mybatis"              level="WARN"/>
    <logger name="com.baomidou.mybatisplus" level="WARN"/>
    <logger name="org.springframework.security" level="WARN"/>

    <!-- ========== 根日志 ========== -->
    <springProfile name="dev">
        <root level="INFO">
            <appender-ref ref="CONSOLE"/>
        </root>
    </springProfile>

    <springProfile name="prod">
        <root level="WARN">
            <appender-ref ref="ASYNC_FILE"/>
            <appender-ref ref="FILE_ERROR"/>
        </root>
    </springProfile>

</configuration>
